spectres/__init__.py
spectres/spectral_resampling.py
spectres/spectral_resampling_numba.py
spectres/spectres_numba_speed_tests.py
spectres-2.2.1.dist-info/LICENSE.txt
spectres-2.2.1.dist-info/METADATA
spectres-2.2.1.dist-info/WHEEL
spectres-2.2.1.dist-info/top_level.txt
spectres-2.2.1.dist-info/RECORD
