Metadata-Version: 2.1
Name: spectres
Version: 2.2.1
Summary: Simple spectral resampling
Home-page: https://spectres.readthedocs.io
Author: Adam Carnall
Author-email: adamc@roe.ac.uk
Project-URL: GitHub, https://github.com/ACCarnall/spectres
Project-URL: ArXiv, https://arxiv.org/abs/1705.05165
License-File: LICENSE.txt
Requires-Dist: numpy
